{"code":"NPG12","name":"SPAMEDICA ECCLESHILL TREATMENT CENTRE","level":"provider","region":"England","months":["2022-04","2022-05","2022-06","2022-07","2022-08","2022-09","2022-10","2022-11","2022-12","2023-01","2023-02","2023-03","2023-04","2023-05","2023-06"],"measures":{"pct18":{"performance":[0.838,0.8622,0.86,0.8697,0.8779,0.8794,0.8865,0.8974,0.864,0.815,0.8355,0.8944,0.9251,0.8636,0.7826],"within_target":[357,363,258,247,230,277,250,280,305,185,127,254,321,152,36],"total":[426,421,300,284,262,315,282,312,353,227,152,284,347,176,46],"data_status":["final","final","final","final","final","final","final","final","final","final","final","final","final","final","final"],"target":0.92},"waitlist":{"value":[426,421,300,284,262,315,282,312,353,227,152,284,347,176,46],"data_status":["final","final","final","final","final","final","final","final","final","final","final","final","final","final","final"]},"longwait":{"w52":[0,1,0,0,0,1,2,1,3,4,0,0,0,0,0],"w65":[0,0,0,0,0,0,0,0,0,1,0,0,0,0,0],"w78":[0,0,0,0,0,0,0,0,0,0,0,0,0,0,0],"w104":[0,0,0,0,0,0,0,0,0,0,0,0,0,0,0],"total":[426,421,300,284,262,315,282,312,353,227,152,284,347,176,46],"data_status":["final","final","final","final","final","final","final","final","final","final","final","final","final","final","final"]}}}